<?xml version = "1.0" encoding = "utf-8" ?>

<helpItems schema="maml">

<command:command xmlns:maml="http://schemas.microsoft.com/maml/2004/10" xmlns:command="http://schemas.microsoft.com/maml/dev/command/2004/10" xmlns:dev="http://schemas.microsoft.com/maml/dev/2004/10" xmlns:MSHelp="http://msdn.microsoft.com/mshelp"><command:details><command:name>Add-DhcpServerv6Scope</command:name><maml:description><maml:para>Adds an IPv6 scope to the Dynamic Host Configuration Protocol (DHCP) server service with the specified parameters.</maml:para></maml:description><maml:copyright><maml:para /></maml:copyright><command:verb>Add</command:verb><command:noun>DhcpServerv6Scope</command:noun><dev:version /></command:details><maml:description><maml:para>The Add-DhcpServerv6Scope cmdlet adds an IPv6 scope to the Dynamic Host Configuration Protocol (DHCP) server service with the specified parameters.</maml:para></maml:description><command:syntax><command:syntaxItem><maml:name>Add-DhcpServerv6Scope</maml:name><command:parameter required="true" variableLength="false" globbing="false" pipelineInput="True (ByPropertyName)" position="2" aliases=""><maml:name>Prefix</maml:name><maml:description><maml:para>Specifies the IPv6 prefix of the scope being added.</maml:para></maml:description><command:parameterValue required="true" variableLength="false">IPAddress</command:parameterValue></command:parameter><command:parameter required="true" variableLength="false" globbing="false" pipelineInput="True (ByPropertyName)" position="3" aliases=""><maml:name>Name</maml:name><maml:description><maml:para>Specifies the name associated with the scope.</maml:para></maml:description><command:parameterValue required="true" variableLength="false">String</command:parameterValue></command:parameter><command:parameter required="false" variableLength="false" globbing="false" pipelineInput="false" position="named" aliases=""><maml:name>AsJob</maml:name><maml:description><maml:para>Runs the cmdlet as a background job. Use this parameter to run commands that take a long time to complete. 
 The cmdlet immediately returns an object that represents the job and then displays the command prompt. You can continue to work in the session while the job completes. To manage the job, use the *-Job cmdlets. To get the job results, use the <maml:navigationLink><maml:linkText>Receive-Job</maml:linkText><maml:uri></maml:uri></maml:navigationLink> cmdlet. 
 For more information about Windows PowerShell® background jobs, see <maml:navigationLink><maml:linkText>about_Jobs</maml:linkText><maml:uri></maml:uri></maml:navigationLink>.</maml:para></maml:description></command:parameter><command:parameter required="false" variableLength="true" globbing="false" pipelineInput="false" position="named" aliases="Session"><maml:name>CimSession</maml:name><maml:description><maml:para>Runs the cmdlet in a remote session or on a remote computer. Enter a computer name or a session object, such as the output of a <maml:navigationLink><maml:linkText>New-CimSession</maml:linkText><maml:uri></maml:uri></maml:navigationLink> or <maml:navigationLink><maml:linkText>Get-CimSession</maml:linkText><maml:uri></maml:uri></maml:navigationLink> cmdlet. The default is the current session on the local computer.</maml:para></maml:description><command:parameterValue required="true" variableLength="true">CimSession[]</command:parameterValue></command:parameter><command:parameter required="false" variableLength="false" globbing="false" pipelineInput="false" position="named" aliases="Cn"><maml:name>ComputerName</maml:name><maml:description><maml:para>Specifies the DNS name, or IPv4 or IPv6 address, of the target computer running the DHCP server service.</maml:para></maml:description><command:parameterValue required="true" variableLength="false">String</command:parameterValue></command:parameter><command:parameter required="false" variableLength="false" globbing="false" pipelineInput="True (ByPropertyName)" position="named" aliases=""><maml:name>Description</maml:name><maml:description><maml:para>Specifies the description associated with the scope.</maml:para></maml:description><command:parameterValue required="true" variableLength="false">String</command:parameterValue></command:parameter><command:parameter required="false" variableLength="false" globbing="false" pipelineInput="false" position="named" aliases=""><maml:name>PassThru</maml:name><maml:description><maml:para>Returns an object representing the item with which you are working. By default, this cmdlet does not generate any output.</maml:para></maml:description></command:parameter><command:parameter required="false" variableLength="false" globbing="false" pipelineInput="True (ByPropertyName)" position="named" aliases=""><maml:name>Preference</maml:name><maml:description><maml:para>Specifies the value for the preference field to be used by the DHCP server service while responding to clients in this subnet. The acceptable values for this parameter are:  0 through 255. 
                         
The default value is 0. </maml:para></maml:description><command:parameterValue required="true" variableLength="false">UInt16</command:parameterValue></command:parameter><command:parameter required="false" variableLength="false" globbing="false" pipelineInput="True (ByPropertyName)" position="named" aliases=""><maml:name>PreferredLifetime</maml:name><maml:description><maml:para>Specifies the preferred life time of the IPv6 address leased by the DHCP server service. The default value is 8 days. 
                         
This parameter value should be same or less than the ValidLifeTime parameter value. </maml:para></maml:description><command:parameterValue required="true" variableLength="false">TimeSpan</command:parameterValue></command:parameter><command:parameter required="false" variableLength="false" globbing="false" pipelineInput="True (ByPropertyName)" position="named" aliases=""><maml:name>State</maml:name><maml:description><maml:para>Specifies the state of the scope. The acceptable values for this parameter are:  Enabled or Disabled.</maml:para></maml:description><command:parameterValue required="true" variableLength="false">String</command:parameterValue></command:parameter><command:parameter required="false" variableLength="false" globbing="false" pipelineInput="True (ByPropertyName)" position="named" aliases=""><maml:name>T1</maml:name><maml:description><maml:para>Specifies the lease renewal time. The default value is 4 days. The DHCP client is expected to use a unicast message to renew the lease at the time specified by this parameter value from the same DHCP server service from which DHCP client had initially obtained the lease. 
                         
This parameter value should be less than the T2 and PreferredLifetime parameter values.</maml:para></maml:description><command:parameterValue required="true" variableLength="false">TimeSpan</command:parameterValue></command:parameter><command:parameter required="false" variableLength="false" globbing="false" pipelineInput="True (ByPropertyName)" position="named" aliases=""><maml:name>T2</maml:name><maml:description><maml:para>Specifies the lease rebind time. The default value is 6.4 days. The DHCP client is expected to use a multi-cast message to renew the lease at the time equal to this parameter value from any DHCP server service if the renewal attempt at time specified by the T1 parameter fails. 
                         
This parameter value should be greater than the T1 parameter value and less than the PreferredLifetime parameter value. </maml:para></maml:description><command:parameterValue required="true" variableLength="false">TimeSpan</command:parameterValue></command:parameter><command:parameter required="false" variableLength="false" globbing="false" pipelineInput="false" position="named" aliases=""><maml:name>ThrottleLimit</maml:name><maml:description><maml:para>Specifies the maximum number of concurrent operations that can be established to run the cmdlet. If this parameter is omitted or a value of 0 is entered, then Windows PowerShell® calculates an optimum throttle limit for the cmdlet based on the number of CIM cmdlets that are running on the computer. The throttle limit applies only to the current cmdlet, not to the session or to the computer.</maml:para></maml:description><command:parameterValue required="true" variableLength="false">Int32</command:parameterValue></command:parameter><command:parameter required="false" variableLength="false" globbing="false" pipelineInput="True (ByPropertyName)" position="named" aliases=""><maml:name>ValidLifeTime</maml:name><maml:description><maml:para>Specifies the valid life time of the IPv6 address leased by the DHCP server service. The default value is 12 days. 
                         
This parameter value should be same or greater than the PreferredLifetime parameter value. </maml:para></maml:description><command:parameterValue required="true" variableLength="false">TimeSpan</command:parameterValue></command:parameter><command:parameter required="false" variableLength="true" globbing="false" pipelineInput="false" position="named"><maml:name>Confirm</maml:name><maml:description><maml:para>Prompts you for confirmation before running the cmdlet.</maml:para></maml:description></command:parameter><command:parameter required="false" variableLength="true" globbing="false" pipelineInput="false" position="named"><maml:name>WhatIf</maml:name><maml:description><maml:para>Shows what would happen if the cmdlet runs. The cmdlet is not run.</maml:para></maml:description></command:parameter></command:syntaxItem></command:syntax><command:parameters><command:parameter required="false" variableLength="false" globbing="false" pipelineInput="false" position="named" aliases=""><maml:name>AsJob</maml:name><maml:description><maml:para>Runs the cmdlet as a background job. Use this parameter to run commands that take a long time to complete. 
 The cmdlet immediately returns an object that represents the job and then displays the command prompt. You can continue to work in the session while the job completes. To manage the job, use the *-Job cmdlets. To get the job results, use the <maml:navigationLink><maml:linkText>Receive-Job</maml:linkText><maml:uri></maml:uri></maml:navigationLink> cmdlet. 
 For more information about Windows PowerShell® background jobs, see <maml:navigationLink><maml:linkText>about_Jobs</maml:linkText><maml:uri></maml:uri></maml:navigationLink>.</maml:para></maml:description><command:parameterValue required="false" variableLength="false">SwitchParameter</command:parameterValue><dev:type><maml:name>SwitchParameter</maml:name><maml:uri /></dev:type><dev:defaultValue></dev:defaultValue></command:parameter><command:parameter required="false" variableLength="true" globbing="false" pipelineInput="false" position="named" aliases="Session"><maml:name>CimSession</maml:name><maml:description><maml:para>Runs the cmdlet in a remote session or on a remote computer. Enter a computer name or a session object, such as the output of a <maml:navigationLink><maml:linkText>New-CimSession</maml:linkText><maml:uri></maml:uri></maml:navigationLink> or <maml:navigationLink><maml:linkText>Get-CimSession</maml:linkText><maml:uri></maml:uri></maml:navigationLink> cmdlet. The default is the current session on the local computer.</maml:para></maml:description><command:parameterValue required="true" variableLength="true">CimSession[]</command:parameterValue><dev:type><maml:name>CimSession[]</maml:name><maml:uri /></dev:type><dev:defaultValue></dev:defaultValue></command:parameter><command:parameter required="false" variableLength="false" globbing="false" pipelineInput="false" position="named" aliases="Cn"><maml:name>ComputerName</maml:name><maml:description><maml:para>Specifies the DNS name, or IPv4 or IPv6 address, of the target computer running the DHCP server service.</maml:para></maml:description><command:parameterValue required="true" variableLength="false">String</command:parameterValue><dev:type><maml:name>String</maml:name><maml:uri /></dev:type><dev:defaultValue></dev:defaultValue></command:parameter><command:parameter required="false" variableLength="false" globbing="false" pipelineInput="True (ByPropertyName)" position="named" aliases=""><maml:name>Description</maml:name><maml:description><maml:para>Specifies the description associated with the scope.</maml:para></maml:description><command:parameterValue required="true" variableLength="false">String</command:parameterValue><dev:type><maml:name>String</maml:name><maml:uri /></dev:type><dev:defaultValue></dev:defaultValue></command:parameter><command:parameter required="true" variableLength="false" globbing="false" pipelineInput="True (ByPropertyName)" position="3" aliases=""><maml:name>Name</maml:name><maml:description><maml:para>Specifies the name associated with the scope.</maml:para></maml:description><command:parameterValue required="true" variableLength="false">String</command:parameterValue><dev:type><maml:name>String</maml:name><maml:uri /></dev:type><dev:defaultValue></dev:defaultValue></command:parameter><command:parameter required="false" variableLength="false" globbing="false" pipelineInput="false" position="named" aliases=""><maml:name>PassThru</maml:name><maml:description><maml:para>Returns an object representing the item with which you are working. By default, this cmdlet does not generate any output.</maml:para></maml:description><command:parameterValue required="false" variableLength="false">SwitchParameter</command:parameterValue><dev:type><maml:name>SwitchParameter</maml:name><maml:uri /></dev:type><dev:defaultValue></dev:defaultValue></command:parameter><command:parameter required="false" variableLength="false" globbing="false" pipelineInput="True (ByPropertyName)" position="named" aliases=""><maml:name>Preference</maml:name><maml:description><maml:para>Specifies the value for the preference field to be used by the DHCP server service while responding to clients in this subnet. The acceptable values for this parameter are:  0 through 255. 
                         
The default value is 0. </maml:para></maml:description><command:parameterValue required="true" variableLength="false">UInt16</command:parameterValue><dev:type><maml:name>UInt16</maml:name><maml:uri /></dev:type><dev:defaultValue>0</dev:defaultValue></command:parameter><command:parameter required="false" variableLength="false" globbing="false" pipelineInput="True (ByPropertyName)" position="named" aliases=""><maml:name>PreferredLifetime</maml:name><maml:description><maml:para>Specifies the preferred life time of the IPv6 address leased by the DHCP server service. The default value is 8 days. 
                         
This parameter value should be same or less than the ValidLifeTime parameter value. </maml:para></maml:description><command:parameterValue required="true" variableLength="false">TimeSpan</command:parameterValue><dev:type><maml:name>TimeSpan</maml:name><maml:uri /></dev:type><dev:defaultValue></dev:defaultValue></command:parameter><command:parameter required="true" variableLength="false" globbing="false" pipelineInput="True (ByPropertyName)" position="2" aliases=""><maml:name>Prefix</maml:name><maml:description><maml:para>Specifies the IPv6 prefix of the scope being added.</maml:para></maml:description><command:parameterValue required="true" variableLength="false">IPAddress</command:parameterValue><dev:type><maml:name>IPAddress</maml:name><maml:uri /></dev:type><dev:defaultValue></dev:defaultValue></command:parameter><command:parameter required="false" variableLength="false" globbing="false" pipelineInput="True (ByPropertyName)" position="named" aliases=""><maml:name>State</maml:name><maml:description><maml:para>Specifies the state of the scope. The acceptable values for this parameter are:  Enabled or Disabled.</maml:para></maml:description><command:parameterValue required="true" variableLength="false">String</command:parameterValue><dev:type><maml:name>String</maml:name><maml:uri /></dev:type><dev:defaultValue></dev:defaultValue></command:parameter><command:parameter required="false" variableLength="false" globbing="false" pipelineInput="True (ByPropertyName)" position="named" aliases=""><maml:name>T1</maml:name><maml:description><maml:para>Specifies the lease renewal time. The default value is 4 days. The DHCP client is expected to use a unicast message to renew the lease at the time specified by this parameter value from the same DHCP server service from which DHCP client had initially obtained the lease. 
                         
This parameter value should be less than the T2 and PreferredLifetime parameter values.</maml:para></maml:description><command:parameterValue required="true" variableLength="false">TimeSpan</command:parameterValue><dev:type><maml:name>TimeSpan</maml:name><maml:uri /></dev:type><dev:defaultValue></dev:defaultValue></command:parameter><command:parameter required="false" variableLength="false" globbing="false" pipelineInput="True (ByPropertyName)" position="named" aliases=""><maml:name>T2</maml:name><maml:description><maml:para>Specifies the lease rebind time. The default value is 6.4 days. The DHCP client is expected to use a multi-cast message to renew the lease at the time equal to this parameter value from any DHCP server service if the renewal attempt at time specified by the T1 parameter fails. 
                         
This parameter value should be greater than the T1 parameter value and less than the PreferredLifetime parameter value. </maml:para></maml:description><command:parameterValue required="true" variableLength="false">TimeSpan</command:parameterValue><dev:type><maml:name>TimeSpan</maml:name><maml:uri /></dev:type><dev:defaultValue></dev:defaultValue></command:parameter><command:parameter required="false" variableLength="false" globbing="false" pipelineInput="false" position="named" aliases=""><maml:name>ThrottleLimit</maml:name><maml:description><maml:para>Specifies the maximum number of concurrent operations that can be established to run the cmdlet. If this parameter is omitted or a value of 0 is entered, then Windows PowerShell® calculates an optimum throttle limit for the cmdlet based on the number of CIM cmdlets that are running on the computer. The throttle limit applies only to the current cmdlet, not to the session or to the computer.</maml:para></maml:description><command:parameterValue required="true" variableLength="false">Int32</command:parameterValue><dev:type><maml:name>Int32</maml:name><maml:uri /></dev:type><dev:defaultValue></dev:defaultValue></command:parameter><command:parameter required="false" variableLength="false" globbing="false" pipelineInput="True (ByPropertyName)" position="named" aliases=""><maml:name>ValidLifeTime</maml:name><maml:description><maml:para>Specifies the valid life time of the IPv6 address leased by the DHCP server service. The default value is 12 days. 
                         
This parameter value should be same or greater than the PreferredLifetime parameter value. </maml:para></maml:description><command:parameterValue required="true" variableLength="false">TimeSpan</command:parameterValue><dev:type><maml:name>TimeSpan</maml:name><maml:uri /></dev:type><dev:defaultValue></dev:defaultValue></command:parameter><command:parameter required="false" variableLength="true" globbing="false" pipelineInput="false" position="named"><maml:name>Confirm</maml:name><maml:description><maml:para>Prompts you for confirmation before running the cmdlet.</maml:para></maml:description><command:parameterValue required="false" variableLength="false">SwitchParameter</command:parameterValue><dev:type><maml:name>SwitchParameter</maml:name><maml:uri /></dev:type><dev:defaultValue>false</dev:defaultValue></command:parameter><command:parameter required="false" variableLength="true" globbing="false" pipelineInput="false" position="named"><maml:name>WhatIf</maml:name><maml:description><maml:para>Shows what would happen if the cmdlet runs. The cmdlet is not run.</maml:para></maml:description><command:parameterValue required="false" variableLength="false">SwitchParameter</command:parameterValue><dev:type><maml:name>SwitchParameter</maml:name><maml:uri /></dev:type><dev:defaultValue>false</dev:defaultValue></command:parameter></command:parameters><command:inputTypes><command:inputType><dev:type><maml:name>Microsoft.Management.Infrastructure.CimInstance#root/Microsoft/Windows/DHCP/DhcpServerv6Scope</maml:name><maml:uri>http://msdn.microsoft.com/library/hh832726.aspx</maml:uri><maml:description><maml:para /></maml:description></dev:type><maml:description><maml:para>The Microsoft.Management.Infrastructure.CimInstance object is a wrapper class that displays Windows Management Instrumentation (WMI) objects. The path after the pound sign (#) provides the namespace and class name for the underlying WMI object.</maml:para></maml:description></command:inputType></command:inputTypes><command:returnValues><command:returnValue><dev:type><maml:name>Microsoft.Management.Infrastructure.CimInstance#root/Microsoft/Windows/DHCP/DhcpServerv6Scope</maml:name><maml:uri>http://msdn.microsoft.com/library/hh832726.aspx</maml:uri><maml:description><maml:para /></maml:description></dev:type><maml:description><maml:para>The Microsoft.Management.Infrastructure.CimInstance object is a wrapper class that displays Windows Management Instrumentation (WMI) objects. The path after the pound sign (#) provides the namespace and class name for the underlying WMI object.</maml:para></maml:description></command:returnValue></command:returnValues><command:terminatingErrors /><command:nonTerminatingErrors /><command:examples><command:example><maml:title>EXAMPLE 1</maml:title><maml:introduction><maml:para></maml:para></maml:introduction><dev:code>PS C:\&gt;Add-DhcpServerv6Scope -Prefix 2001:4898:7020:1020:: -Name "IPv6 Lab-4 Network"

</dev:code><dev:remarks><maml:para>The above command adds a DHCPv6 scope with subnet prefix 2001:4898:7020:1020:: and specified scope name to the DHCP server running on local computer.</maml:para></dev:remarks><command:commandLines><command:commandLine><command:commandText /></command:commandLine></command:commandLines></command:example><command:example><maml:title>EXAMPLE 2</maml:title><maml:introduction><maml:para></maml:para></maml:introduction><dev:code>PS C:\&gt;Add-DhcpServerv6Scope -ComputerName dhcpserver.contoso.com -Prefix 2001:4898:7020:1020:: -Name "IPv6 Lab-4 Network" -PreferredLifeTime 4.00:00:00 -ValidLifeTime 6.00:00:00 -State Inactive

</dev:code><dev:remarks><maml:para>This example adds an inactive DHCPv6 scope with the subnet prefix 2001:4898:7020:1020::, specifies the scope name, sets the preferred lifetime to 4 days, and sets the valid lifetime to 6 days to the DHCP server service running on the computer named dhcpserver.contoso.com.</maml:para></dev:remarks><command:commandLines><command:commandLine><command:commandText /></command:commandLine></command:commandLines></command:example></command:examples><maml:relatedLinks><maml:navigationLink><maml:linkText>Online Version:</maml:linkText><maml:uri>http://go.microsoft.com/fwlink/?LinkID=289283</maml:uri></maml:navigationLink><maml:navigationLink><maml:linkText>Get-DhcpServerv6Scope</maml:linkText><maml:uri /></maml:navigationLink><maml:navigationLink><maml:linkText>Get-DhcpServerv6ScopeStatistics</maml:linkText><maml:uri /></maml:navigationLink><maml:navigationLink><maml:linkText>Remove-DhcpServerv6Scope</maml:linkText><maml:uri /></maml:navigationLink><maml:navigationLink><maml:linkText>Set-DhcpServerv6Scope</maml:linkText><maml:uri /></maml:navigationLink></maml:relatedLinks></command:command>

<command:command xmlns:maml="http://schemas.microsoft.com/maml/2004/10" xmlns:command="http://schemas.microsoft.com/maml/dev/command/2004/10" xmlns:dev="http://schemas.microsoft.com/maml/dev/2004/10" xmlns:MSHelp="http://msdn.microsoft.com/mshelp"><command:details><command:name>Get-DhcpServerv6Scope</command:name><maml:description><maml:para>Gets the scope information for the specified IPv6 prefixes on the Dynamic Host Configuration Protocol (DHCP) server service.</maml:para></maml:description><maml:copyright><maml:para /></maml:copyright><command:verb>Get</command:verb><command:noun>DhcpServerv6Scope</command:noun><dev:version /></command:details><maml:description><maml:para>The Get-DhcpServerv6Scope cmdlet gets the scope information for the specified IPv6 prefixes on the Dynamic Host Configuration Protocol (DHCP) server service.</maml:para></maml:description><command:syntax><command:syntaxItem><maml:name>Get-DhcpServerv6Scope</maml:name><command:parameter required="false" variableLength="true" globbing="false" pipelineInput="True (ByPropertyName)" position="2" aliases=""><maml:name>Prefix</maml:name><maml:description><maml:para>Specifies the IPv6 prefixes for which the scope information is being requested.</maml:para></maml:description><command:parameterValue required="true" variableLength="true">IPAddress[]</command:parameterValue></command:parameter><command:parameter required="false" variableLength="false" globbing="false" pipelineInput="false" position="named" aliases=""><maml:name>AsJob</maml:name><maml:description><maml:para>Runs the cmdlet as a background job. Use this parameter to run commands that take a long time to complete. 
 The cmdlet immediately returns an object that represents the job and then displays the command prompt. You can continue to work in the session while the job completes. To manage the job, use the *-Job cmdlets. To get the job results, use the <maml:navigationLink><maml:linkText>Receive-Job</maml:linkText><maml:uri></maml:uri></maml:navigationLink> cmdlet. 
 For more information about Windows PowerShell® background jobs, see <maml:navigationLink><maml:linkText>about_Jobs</maml:linkText><maml:uri></maml:uri></maml:navigationLink>.</maml:para></maml:description></command:parameter><command:parameter required="false" variableLength="true" globbing="false" pipelineInput="false" position="named" aliases="Session"><maml:name>CimSession</maml:name><maml:description><maml:para>Runs the cmdlet in a remote session or on a remote computer. Enter a computer name or a session object, such as the output of a <maml:navigationLink><maml:linkText>New-CimSession</maml:linkText><maml:uri></maml:uri></maml:navigationLink> or <maml:navigationLink><maml:linkText>Get-CimSession</maml:linkText><maml:uri></maml:uri></maml:navigationLink> cmdlet. The default is the current session on the local computer.</maml:para></maml:description><command:parameterValue required="true" variableLength="true">CimSession[]</command:parameterValue></command:parameter><command:parameter required="false" variableLength="false" globbing="false" pipelineInput="false" position="named" aliases="Cn"><maml:name>ComputerName</maml:name><maml:description><maml:para>Specifies the DNS name, or IPv4 or IPv6 address, of the target computer running the DHCP server service.</maml:para></maml:description><command:parameterValue required="true" variableLength="false">String</command:parameterValue></command:parameter><command:parameter required="false" variableLength="false" globbing="false" pipelineInput="false" position="named" aliases=""><maml:name>ThrottleLimit</maml:name><maml:description><maml:para>Specifies the maximum number of concurrent operations that can be established to run the cmdlet. If this parameter is omitted or a value of 0 is entered, then Windows PowerShell® calculates an optimum throttle limit for the cmdlet based on the number of CIM cmdlets that are running on the computer. The throttle limit applies only to the current cmdlet, not to the session or to the computer.</maml:para></maml:description><command:parameterValue required="true" variableLength="false">Int32</command:parameterValue></command:parameter></command:syntaxItem></command:syntax><command:parameters><command:parameter required="false" variableLength="false" globbing="false" pipelineInput="false" position="named" aliases=""><maml:name>AsJob</maml:name><maml:description><maml:para>Runs the cmdlet as a background job. Use this parameter to run commands that take a long time to complete. 
 The cmdlet immediately returns an object that represents the job and then displays the command prompt. You can continue to work in the session while the job completes. To manage the job, use the *-Job cmdlets. To get the job results, use the <maml:navigationLink><maml:linkText>Receive-Job</maml:linkText><maml:uri></maml:uri></maml:navigationLink> cmdlet. 
 For more information about Windows PowerShell® background jobs, see <maml:navigationLink><maml:linkText>about_Jobs</maml:linkText><maml:uri></maml:uri></maml:navigationLink>.</maml:para></maml:description><command:parameterValue required="false" variableLength="false">SwitchParameter</command:parameterValue><dev:type><maml:name>SwitchParameter</maml:name><maml:uri /></dev:type><dev:defaultValue></dev:defaultValue></command:parameter><command:parameter required="false" variableLength="true" globbing="false" pipelineInput="false" position="named" aliases="Session"><maml:name>CimSession</maml:name><maml:description><maml:para>Runs the cmdlet in a remote session or on a remote computer. Enter a computer name or a session object, such as the output of a <maml:navigationLink><maml:linkText>New-CimSession</maml:linkText><maml:uri></maml:uri></maml:navigationLink> or <maml:navigationLink><maml:linkText>Get-CimSession</maml:linkText><maml:uri></maml:uri></maml:navigationLink> cmdlet. The default is the current session on the local computer.</maml:para></maml:description><command:parameterValue required="true" variableLength="true">CimSession[]</command:parameterValue><dev:type><maml:name>CimSession[]</maml:name><maml:uri /></dev:type><dev:defaultValue></dev:defaultValue></command:parameter><command:parameter required="false" variableLength="false" globbing="false" pipelineInput="false" position="named" aliases="Cn"><maml:name>ComputerName</maml:name><maml:description><maml:para>Specifies the DNS name, or IPv4 or IPv6 address, of the target computer running the DHCP server service.</maml:para></maml:description><command:parameterValue required="true" variableLength="false">String</command:parameterValue><dev:type><maml:name>String</maml:name><maml:uri /></dev:type><dev:defaultValue></dev:defaultValue></command:parameter><command:parameter required="false" variableLength="true" globbing="false" pipelineInput="True (ByPropertyName)" position="2" aliases=""><maml:name>Prefix</maml:name><maml:description><maml:para>Specifies the IPv6 prefixes for which the scope information is being requested.</maml:para></maml:description><command:parameterValue required="true" variableLength="true">IPAddress[]</command:parameterValue><dev:type><maml:name>IPAddress[]</maml:name><maml:uri /></dev:type><dev:defaultValue></dev:defaultValue></command:parameter><command:parameter required="false" variableLength="false" globbing="false" pipelineInput="false" position="named" aliases=""><maml:name>ThrottleLimit</maml:name><maml:description><maml:para>Specifies the maximum number of concurrent operations that can be established to run the cmdlet. If this parameter is omitted or a value of 0 is entered, then Windows PowerShell® calculates an optimum throttle limit for the cmdlet based on the number of CIM cmdlets that are running on the computer. The throttle limit applies only to the current cmdlet, not to the session or to the computer.</maml:para></maml:description><command:parameterValue required="true" variableLength="false">Int32</command:parameterValue><dev:type><maml:name>Int32</maml:name><maml:uri /></dev:type><dev:defaultValue></dev:defaultValue></command:parameter></command:parameters><command:inputTypes><command:inputType><dev:type><maml:name>Microsoft.Management.Infrastructure.CimInstance#root/Microsoft/Windows/DHCP/DhcpServerv6Scope</maml:name><maml:uri>http://msdn.microsoft.com/library/hh832726.aspx</maml:uri><maml:description><maml:para /></maml:description></dev:type><maml:description><maml:para>The Microsoft.Management.Infrastructure.CimInstance object is a wrapper class that displays Windows Management Instrumentation (WMI) objects. The path after the pound sign (#) provides the namespace and class name for the underlying WMI object.</maml:para></maml:description></command:inputType></command:inputTypes><command:returnValues><command:returnValue><dev:type><maml:name>Microsoft.Management.Infrastructure.CimInstance#root/Microsoft/Windows/DHCP/DhcpServerv6Scope[]</maml:name><maml:uri>http://msdn.microsoft.com/library/hh832726.aspx</maml:uri><maml:description><maml:para /></maml:description></dev:type><maml:description><maml:para>The Microsoft.Management.Infrastructure.CimInstance object is a wrapper class that displays Windows Management Instrumentation (WMI) objects. The path after the pound sign (#) provides the namespace and class name for the underlying WMI object.</maml:para></maml:description></command:returnValue></command:returnValues><command:terminatingErrors /><command:nonTerminatingErrors /><command:examples><command:example><maml:title>EXAMPLE 1</maml:title><maml:introduction><maml:para></maml:para></maml:introduction><dev:code>PS C:\&gt;Get-DhcpServerv6Scope -ComputerName dhcpserver.contoso.com

</dev:code><dev:remarks><maml:para>This example gets the information for all of the DHCPv6 scopes on the DHCP server service.</maml:para></dev:remarks><command:commandLines><command:commandLine><command:commandText /></command:commandLine></command:commandLines></command:example><command:example><maml:title>EXAMPLE 2</maml:title><maml:introduction><maml:para></maml:para></maml:introduction><dev:code>PS C:\&gt;Get-DhcpServerv6Scope -ComputerName dhcpserver.contoso.com -Prefix 2001:4898:7020:1020::

</dev:code><dev:remarks><maml:para>This example gets the information for the specified DHCPv6 scope on the DHCP server service.</maml:para></dev:remarks><command:commandLines><command:commandLine><command:commandText /></command:commandLine></command:commandLines></command:example></command:examples><maml:relatedLinks><maml:navigationLink><maml:linkText>Online Version:</maml:linkText><maml:uri>http://go.microsoft.com/fwlink/?LinkID=289323</maml:uri></maml:navigationLink><maml:navigationLink><maml:linkText>Add-DhcpServerv6Scope</maml:linkText><maml:uri /></maml:navigationLink><maml:navigationLink><maml:linkText>Get-DhcpServerv6ScopeStatistics</maml:linkText><maml:uri /></maml:navigationLink><maml:navigationLink><maml:linkText>Remove-DhcpServerv6Scope</maml:linkText><maml:uri /></maml:navigationLink><maml:navigationLink><maml:linkText>Set-DhcpServerv6Scope</maml:linkText><maml:uri /></maml:navigationLink></maml:relatedLinks></command:command>

<command:command xmlns:maml="http://schemas.microsoft.com/maml/2004/10" xmlns:command="http://schemas.microsoft.com/maml/dev/command/2004/10" xmlns:dev="http://schemas.microsoft.com/maml/dev/2004/10" xmlns:MSHelp="http://msdn.microsoft.com/mshelp"><command:details><command:name>Remove-DhcpServerv6Scope</command:name><maml:description><maml:para>Deletes the IPv6 Scopes from the Dynamic Host Configuration Protocol (DHCP) server service corresponding to the specified prefixes.</maml:para></maml:description><maml:copyright><maml:para /></maml:copyright><command:verb>Remove</command:verb><command:noun>DhcpServerv6Scope</command:noun><dev:version /></command:details><maml:description><maml:para>The Remove-DhcpServerv6Scope cmdlet deletes the IPv6 Scopes from the Dynamic Host Configuration Protocol (DHCP) server service corresponding to the specified prefixes. Deleting a scope deletes all of the associated settings and leases, if any are present in the scope.</maml:para></maml:description><command:syntax><command:syntaxItem><maml:name>Remove-DhcpServerv6Scope</maml:name><command:parameter required="true" variableLength="true" globbing="false" pipelineInput="True (ByPropertyName)" position="2" aliases=""><maml:name>Prefix</maml:name><maml:description><maml:para>Specifies one or more IPv6 subnet prefixes of the scopes being deleted.</maml:para></maml:description><command:parameterValue required="true" variableLength="true">IPAddress[]</command:parameterValue></command:parameter><command:parameter required="false" variableLength="false" globbing="false" pipelineInput="false" position="named" aliases=""><maml:name>AsJob</maml:name><maml:description><maml:para>Runs the cmdlet as a background job. Use this parameter to run commands that take a long time to complete. 
 The cmdlet immediately returns an object that represents the job and then displays the command prompt. You can continue to work in the session while the job completes. To manage the job, use the *-Job cmdlets. To get the job results, use the <maml:navigationLink><maml:linkText>Receive-Job</maml:linkText><maml:uri></maml:uri></maml:navigationLink> cmdlet. 
 For more information about Windows PowerShell® background jobs, see <maml:navigationLink><maml:linkText>about_Jobs</maml:linkText><maml:uri></maml:uri></maml:navigationLink>.</maml:para></maml:description></command:parameter><command:parameter required="false" variableLength="true" globbing="false" pipelineInput="false" position="named" aliases="Session"><maml:name>CimSession</maml:name><maml:description><maml:para>Runs the cmdlet in a remote session or on a remote computer. Enter a computer name or a session object, such as the output of a <maml:navigationLink><maml:linkText>New-CimSession</maml:linkText><maml:uri></maml:uri></maml:navigationLink> or <maml:navigationLink><maml:linkText>Get-CimSession</maml:linkText><maml:uri></maml:uri></maml:navigationLink> cmdlet. The default is the current session on the local computer.</maml:para></maml:description><command:parameterValue required="true" variableLength="true">CimSession[]</command:parameterValue></command:parameter><command:parameter required="false" variableLength="false" globbing="false" pipelineInput="false" position="named" aliases="Cn"><maml:name>ComputerName</maml:name><maml:description><maml:para>Specifies the DNS name, or IPv4 or IPv6 address, of the target computer running the DHCP server service.</maml:para></maml:description><command:parameterValue required="true" variableLength="false">String</command:parameterValue></command:parameter><command:parameter required="false" variableLength="false" globbing="false" pipelineInput="false" position="named" aliases=""><maml:name>Force</maml:name><maml:description><maml:para>Specifies that the scope will be deleted even if there are active leases in the scope.</maml:para></maml:description></command:parameter><command:parameter required="false" variableLength="false" globbing="false" pipelineInput="false" position="named" aliases=""><maml:name>Passthru</maml:name><maml:description><maml:para>Returns an object representing the item with which you are working. By default, this cmdlet does not generate any output.</maml:para></maml:description></command:parameter><command:parameter required="false" variableLength="false" globbing="false" pipelineInput="false" position="named" aliases=""><maml:name>ThrottleLimit</maml:name><maml:description><maml:para>Specifies the maximum number of concurrent operations that can be established to run the cmdlet. If this parameter is omitted or a value of 0 is entered, then Windows PowerShell® calculates an optimum throttle limit for the cmdlet based on the number of CIM cmdlets that are running on the computer. The throttle limit applies only to the current cmdlet, not to the session or to the computer.</maml:para></maml:description><command:parameterValue required="true" variableLength="false">Int32</command:parameterValue></command:parameter><command:parameter required="false" variableLength="true" globbing="false" pipelineInput="false" position="named"><maml:name>Confirm</maml:name><maml:description><maml:para>Prompts you for confirmation before running the cmdlet.</maml:para></maml:description></command:parameter><command:parameter required="false" variableLength="true" globbing="false" pipelineInput="false" position="named"><maml:name>WhatIf</maml:name><maml:description><maml:para>Shows what would happen if the cmdlet runs. The cmdlet is not run.</maml:para></maml:description></command:parameter></command:syntaxItem></command:syntax><command:parameters><command:parameter required="false" variableLength="false" globbing="false" pipelineInput="false" position="named" aliases=""><maml:name>AsJob</maml:name><maml:description><maml:para>Runs the cmdlet as a background job. Use this parameter to run commands that take a long time to complete. 
 The cmdlet immediately returns an object that represents the job and then displays the command prompt. You can continue to work in the session while the job completes. To manage the job, use the *-Job cmdlets. To get the job results, use the <maml:navigationLink><maml:linkText>Receive-Job</maml:linkText><maml:uri></maml:uri></maml:navigationLink> cmdlet. 
 For more information about Windows PowerShell® background jobs, see <maml:navigationLink><maml:linkText>about_Jobs</maml:linkText><maml:uri></maml:uri></maml:navigationLink>.</maml:para></maml:description><command:parameterValue required="false" variableLength="false">SwitchParameter</command:parameterValue><dev:type><maml:name>SwitchParameter</maml:name><maml:uri /></dev:type><dev:defaultValue></dev:defaultValue></command:parameter><command:parameter required="false" variableLength="true" globbing="false" pipelineInput="false" position="named" aliases="Session"><maml:name>CimSession</maml:name><maml:description><maml:para>Runs the cmdlet in a remote session or on a remote computer. Enter a computer name or a session object, such as the output of a <maml:navigationLink><maml:linkText>New-CimSession</maml:linkText><maml:uri></maml:uri></maml:navigationLink> or <maml:navigationLink><maml:linkText>Get-CimSession</maml:linkText><maml:uri></maml:uri></maml:navigationLink> cmdlet. The default is the current session on the local computer.</maml:para></maml:description><command:parameterValue required="true" variableLength="true">CimSession[]</command:parameterValue><dev:type><maml:name>CimSession[]</maml:name><maml:uri /></dev:type><dev:defaultValue></dev:defaultValue></command:parameter><command:parameter required="false" variableLength="false" globbing="false" pipelineInput="false" position="named" aliases="Cn"><maml:name>ComputerName</maml:name><maml:description><maml:para>Specifies the DNS name, or IPv4 or IPv6 address, of the target computer running the DHCP server service.</maml:para></maml:description><command:parameterValue required="true" variableLength="false">String</command:parameterValue><dev:type><maml:name>String</maml:name><maml:uri /></dev:type><dev:defaultValue></dev:defaultValue></command:parameter><command:parameter required="false" variableLength="false" globbing="false" pipelineInput="false" position="named" aliases=""><maml:name>Force</maml:name><maml:description><maml:para>Specifies that the scope will be deleted even if there are active leases in the scope.</maml:para></maml:description><command:parameterValue required="false" variableLength="false">SwitchParameter</command:parameterValue><dev:type><maml:name>SwitchParameter</maml:name><maml:uri /></dev:type><dev:defaultValue></dev:defaultValue></command:parameter><command:parameter required="false" variableLength="false" globbing="false" pipelineInput="false" position="named" aliases=""><maml:name>Passthru</maml:name><maml:description><maml:para>Returns an object representing the item with which you are working. By default, this cmdlet does not generate any output.</maml:para></maml:description><command:parameterValue required="false" variableLength="false">SwitchParameter</command:parameterValue><dev:type><maml:name>SwitchParameter</maml:name><maml:uri /></dev:type><dev:defaultValue></dev:defaultValue></command:parameter><command:parameter required="true" variableLength="true" globbing="false" pipelineInput="True (ByPropertyName)" position="2" aliases=""><maml:name>Prefix</maml:name><maml:description><maml:para>Specifies one or more IPv6 subnet prefixes of the scopes being deleted.</maml:para></maml:description><command:parameterValue required="true" variableLength="true">IPAddress[]</command:parameterValue><dev:type><maml:name>IPAddress[]</maml:name><maml:uri /></dev:type><dev:defaultValue></dev:defaultValue></command:parameter><command:parameter required="false" variableLength="false" globbing="false" pipelineInput="false" position="named" aliases=""><maml:name>ThrottleLimit</maml:name><maml:description><maml:para>Specifies the maximum number of concurrent operations that can be established to run the cmdlet. If this parameter is omitted or a value of 0 is entered, then Windows PowerShell® calculates an optimum throttle limit for the cmdlet based on the number of CIM cmdlets that are running on the computer. The throttle limit applies only to the current cmdlet, not to the session or to the computer.</maml:para></maml:description><command:parameterValue required="true" variableLength="false">Int32</command:parameterValue><dev:type><maml:name>Int32</maml:name><maml:uri /></dev:type><dev:defaultValue></dev:defaultValue></command:parameter><command:parameter required="false" variableLength="true" globbing="false" pipelineInput="false" position="named"><maml:name>Confirm</maml:name><maml:description><maml:para>Prompts you for confirmation before running the cmdlet.</maml:para></maml:description><command:parameterValue required="false" variableLength="false">SwitchParameter</command:parameterValue><dev:type><maml:name>SwitchParameter</maml:name><maml:uri /></dev:type><dev:defaultValue>false</dev:defaultValue></command:parameter><command:parameter required="false" variableLength="true" globbing="false" pipelineInput="false" position="named"><maml:name>WhatIf</maml:name><maml:description><maml:para>Shows what would happen if the cmdlet runs. The cmdlet is not run.</maml:para></maml:description><command:parameterValue required="false" variableLength="false">SwitchParameter</command:parameterValue><dev:type><maml:name>SwitchParameter</maml:name><maml:uri /></dev:type><dev:defaultValue>false</dev:defaultValue></command:parameter></command:parameters><command:inputTypes><command:inputType><dev:type><maml:name>Microsoft.Management.Infrastructure.CimInstance#root/Microsoft/Windows/DHCP/DhcpServerv6Scope</maml:name><maml:uri>http://msdn.microsoft.com/library/hh832726.aspx</maml:uri><maml:description><maml:para /></maml:description></dev:type><maml:description><maml:para>The Microsoft.Management.Infrastructure.CimInstance object is a wrapper class that displays Windows Management Instrumentation (WMI) objects. The path after the pound sign (#) provides the namespace and class name for the underlying WMI object.</maml:para></maml:description></command:inputType></command:inputTypes><command:returnValues><command:returnValue><dev:type><maml:name>Microsoft.Management.Infrastructure.CimInstance#root/Microsoft/Windows/DHCP/DhcpServerv6Scope[]</maml:name><maml:uri>http://msdn.microsoft.com/library/hh832726.aspx</maml:uri><maml:description><maml:para /></maml:description></dev:type><maml:description><maml:para>The Microsoft.Management.Infrastructure.CimInstance object is a wrapper class that displays Windows Management Instrumentation (WMI) objects. The path after the pound sign (#) provides the namespace and class name for the underlying WMI object.</maml:para></maml:description></command:returnValue></command:returnValues><command:terminatingErrors /><command:nonTerminatingErrors /><command:examples><command:example><maml:title>EXAMPLE 1</maml:title><maml:introduction><maml:para></maml:para></maml:introduction><dev:code>PS C:\&gt;Remove-DhcpServerv6Scope -ComputerName dhcpserver.contoso.com -Prefix 2001:4898:7020:1020::

</dev:code><dev:remarks><maml:para>This example deletes the specified DHCPv6 scope from the specified DHCP server service.</maml:para></dev:remarks><command:commandLines><command:commandLine><command:commandText /></command:commandLine></command:commandLines></command:example><command:example><maml:title>EXAMPLE 2</maml:title><maml:introduction><maml:para></maml:para></maml:introduction><dev:code>PS C:\&gt;Remove-DhcpServerv6Scope -ComputerName dhcpserver.contoso.com -Prefix 2001:4898:7020:1020:: -Force

</dev:code><dev:remarks><maml:para>This example deletes the specified DHCPv6 scope from the specified DHCP server service without requesting user confirmation even if the scope is active or contains active client leases.</maml:para></dev:remarks><command:commandLines><command:commandLine><command:commandText /></command:commandLine></command:commandLines></command:example><command:example><maml:title>EXAMPLE 3</maml:title><maml:introduction><maml:para></maml:para></maml:introduction><dev:code>PS C:\&gt;Get-DhcpServerv6Scope | Where-Object -FilterScript { $_.State -Eq "Inactive" } | Remove-DhcpServerv6Scope -Force -Passthru

</dev:code><dev:remarks><maml:para>This example deletes all of the disabled scopes on the DHCP server service. The Get-DhcpServerv6Scope cmdlet returns the scope objects and pipes the objects into the <maml:navigationLink><maml:linkText>Where-Object</maml:linkText><maml:uri></maml:uri></maml:navigationLink> cmdlet. The <maml:navigationLink><maml:linkText>Where-Object</maml:linkText><maml:uri></maml:uri></maml:navigationLink> cmdlet filters the scope objects for the state being InActive (or disabled) and pipes the objects into this cmdlet, which deletes the disabled scopes passed through the pipeline. If non-empty scopes are deleted without the Force parameter, then the cmdlet displays an error. This cmdlet does not prompt for user confirmation. Active scopes that are empty get deleted without the Force parameter.</maml:para></dev:remarks><command:commandLines><command:commandLine><command:commandText /></command:commandLine></command:commandLines></command:example></command:examples><maml:relatedLinks><maml:navigationLink><maml:linkText>Online Version:</maml:linkText><maml:uri>http://go.microsoft.com/fwlink/?LinkID=289382</maml:uri></maml:navigationLink><maml:navigationLink><maml:linkText>Where-Object</maml:linkText><maml:uri></maml:uri></maml:navigationLink><maml:navigationLink><maml:linkText>Add-DhcpServerv6Scope</maml:linkText><maml:uri /></maml:navigationLink><maml:navigationLink><maml:linkText>Get-DhcpServerv6Scope</maml:linkText><maml:uri /></maml:navigationLink><maml:navigationLink><maml:linkText>Get-DhcpServerv6ScopeStatistics</maml:linkText><maml:uri /></maml:navigationLink><maml:navigationLink><maml:linkText>Set-DhcpServerv6Scope</maml:linkText><maml:uri /></maml:navigationLink></maml:relatedLinks></command:command>

<command:command xmlns:maml="http://schemas.microsoft.com/maml/2004/10" xmlns:command="http://schemas.microsoft.com/maml/dev/command/2004/10" xmlns:dev="http://schemas.microsoft.com/maml/dev/2004/10" xmlns:MSHelp="http://msdn.microsoft.com/mshelp"><command:details><command:name>Set-DhcpServerv6Scope</command:name><maml:description><maml:para>Modifies the properties of the IPv6 scope on the Dynamic Host Configuration Protocol (DHCP) server service.</maml:para></maml:description><maml:copyright><maml:para /></maml:copyright><command:verb>Set</command:verb><command:noun>DhcpServerv6Scope</command:noun><dev:version /></command:details><maml:description><maml:para>The Set-DhcpServerv6Scope cmdlet modifies the properties of the IPv6 scope on the Dynamic Host Configuration Protocol (DHCP) server service.</maml:para></maml:description><command:syntax><command:syntaxItem><maml:name>Set-DhcpServerv6Scope</maml:name><command:parameter required="true" variableLength="false" globbing="false" pipelineInput="True (ByPropertyName)" position="2" aliases=""><maml:name>Prefix</maml:name><maml:description><maml:para>Specifies the IPv6 subnet prefix of the scope for which the properties are modified.</maml:para></maml:description><command:parameterValue required="true" variableLength="false">IPAddress</command:parameterValue></command:parameter><command:parameter required="false" variableLength="false" globbing="false" pipelineInput="false" position="named" aliases=""><maml:name>AsJob</maml:name><maml:description><maml:para>Runs the cmdlet as a background job. Use this parameter to run commands that take a long time to complete. 
 The cmdlet immediately returns an object that represents the job and then displays the command prompt. You can continue to work in the session while the job completes. To manage the job, use the *-Job cmdlets. To get the job results, use the <maml:navigationLink><maml:linkText>Receive-Job</maml:linkText><maml:uri></maml:uri></maml:navigationLink> cmdlet. 
 For more information about Windows PowerShell® background jobs, see <maml:navigationLink><maml:linkText>about_Jobs</maml:linkText><maml:uri></maml:uri></maml:navigationLink>.</maml:para></maml:description></command:parameter><command:parameter required="false" variableLength="true" globbing="false" pipelineInput="false" position="named" aliases="Session"><maml:name>CimSession</maml:name><maml:description><maml:para>Runs the cmdlet in a remote session or on a remote computer. Enter a computer name or a session object, such as the output of a <maml:navigationLink><maml:linkText>New-CimSession</maml:linkText><maml:uri></maml:uri></maml:navigationLink> or <maml:navigationLink><maml:linkText>Get-CimSession</maml:linkText><maml:uri></maml:uri></maml:navigationLink> cmdlet. The default is the current session on the local computer.</maml:para></maml:description><command:parameterValue required="true" variableLength="true">CimSession[]</command:parameterValue></command:parameter><command:parameter required="false" variableLength="false" globbing="false" pipelineInput="false" position="named" aliases="Cn"><maml:name>ComputerName</maml:name><maml:description><maml:para>Specifies the DNS name, or IPv4 or IPv6 address, of the target computer running the DHCP server service.</maml:para></maml:description><command:parameterValue required="true" variableLength="false">String</command:parameterValue></command:parameter><command:parameter required="false" variableLength="false" globbing="false" pipelineInput="True (ByPropertyName)" position="named" aliases=""><maml:name>Description</maml:name><maml:description><maml:para>Specifies the description to set on the scope.</maml:para></maml:description><command:parameterValue required="true" variableLength="false">String</command:parameterValue></command:parameter><command:parameter required="false" variableLength="false" globbing="false" pipelineInput="True (ByPropertyName)" position="named" aliases=""><maml:name>Name</maml:name><maml:description><maml:para>Specifies the new name to set for the scope.</maml:para></maml:description><command:parameterValue required="true" variableLength="false">String</command:parameterValue></command:parameter><command:parameter required="false" variableLength="false" globbing="false" pipelineInput="false" position="named" aliases=""><maml:name>PassThru</maml:name><maml:description><maml:para>Returns an object representing the item with which you are working. By default, this cmdlet does not generate any output.</maml:para></maml:description></command:parameter><command:parameter required="false" variableLength="false" globbing="false" pipelineInput="True (ByPropertyName)" position="named" aliases=""><maml:name>Preference</maml:name><maml:description><maml:para>Specifies the preference value of the DHCP server service. The DHCP server service with the lowest preference value is selected by the DHCP client in case the client gets responses from more than one DHCP server service.</maml:para></maml:description><command:parameterValue required="true" variableLength="false">UInt16</command:parameterValue></command:parameter><command:parameter required="false" variableLength="false" globbing="false" pipelineInput="True (ByPropertyName)" position="named" aliases=""><maml:name>PreferredLifeTime</maml:name><maml:description><maml:para>Specifies the preferred life time of the IPv6 address leased by the DHCP server service. 
                         
This parameter value should be same or less than the ValidLifeTime parameter value.</maml:para></maml:description><command:parameterValue required="true" variableLength="false">TimeSpan</command:parameterValue></command:parameter><command:parameter required="false" variableLength="false" globbing="false" pipelineInput="True (ByPropertyName)" position="named" aliases=""><maml:name>State</maml:name><maml:description><maml:para>Specifies the state of the scope. The acceptable values for this parameter are:  Active or Inactive.</maml:para></maml:description><command:parameterValue required="true" variableLength="false">String</command:parameterValue></command:parameter><command:parameter required="false" variableLength="false" globbing="false" pipelineInput="True (ByPropertyName)" position="named" aliases=""><maml:name>T1</maml:name><maml:description><maml:para>Specifies the lease renewal time. The DHCP client is expected to use a unicast message to renew the lease at the time specifies by this parameter value from the same DHCP server service from which DHCP client had initially obtained the lease. This parameter value should be less than the T2 and PreferredLifetime parameter values for the scope.</maml:para></maml:description><command:parameterValue required="true" variableLength="false">TimeSpan</command:parameterValue></command:parameter><command:parameter required="false" variableLength="false" globbing="false" pipelineInput="True (ByPropertyName)" position="named" aliases=""><maml:name>T2</maml:name><maml:description><maml:para>Specifies the lease rebind time. The client is expected to use a multi-cast message to renew the lease at the time equal to this parameter value from any DHCP server service if the renewal attempt at time specified by the T1 parameter fails. 
                         
This parameter value should be greater than the T1 parameter value and less than the PreferredLifetime parameter value.</maml:para></maml:description><command:parameterValue required="true" variableLength="false">TimeSpan</command:parameterValue></command:parameter><command:parameter required="false" variableLength="false" globbing="false" pipelineInput="false" position="named" aliases=""><maml:name>ThrottleLimit</maml:name><maml:description><maml:para>Specifies the maximum number of concurrent operations that can be established to run the cmdlet. If this parameter is omitted or a value of 0 is entered, then Windows PowerShell® calculates an optimum throttle limit for the cmdlet based on the number of CIM cmdlets that are running on the computer. The throttle limit applies only to the current cmdlet, not to the session or to the computer.</maml:para></maml:description><command:parameterValue required="true" variableLength="false">Int32</command:parameterValue></command:parameter><command:parameter required="false" variableLength="false" globbing="false" pipelineInput="True (ByPropertyName)" position="named" aliases=""><maml:name>ValidLifeTime</maml:name><maml:description><maml:para>Specifies the valid life time of the IPv6 address leased by the DHCP server service. 
                         
This parameter value should be same or greater than the PreferredLifetime parameter value.</maml:para></maml:description><command:parameterValue required="true" variableLength="false">TimeSpan</command:parameterValue></command:parameter><command:parameter required="false" variableLength="true" globbing="false" pipelineInput="false" position="named"><maml:name>Confirm</maml:name><maml:description><maml:para>Prompts you for confirmation before running the cmdlet.</maml:para></maml:description></command:parameter><command:parameter required="false" variableLength="true" globbing="false" pipelineInput="false" position="named"><maml:name>WhatIf</maml:name><maml:description><maml:para>Shows what would happen if the cmdlet runs. The cmdlet is not run.</maml:para></maml:description></command:parameter></command:syntaxItem></command:syntax><command:parameters><command:parameter required="false" variableLength="false" globbing="false" pipelineInput="false" position="named" aliases=""><maml:name>AsJob</maml:name><maml:description><maml:para>Runs the cmdlet as a background job. Use this parameter to run commands that take a long time to complete. 
 The cmdlet immediately returns an object that represents the job and then displays the command prompt. You can continue to work in the session while the job completes. To manage the job, use the *-Job cmdlets. To get the job results, use the <maml:navigationLink><maml:linkText>Receive-Job</maml:linkText><maml:uri></maml:uri></maml:navigationLink> cmdlet. 
 For more information about Windows PowerShell® background jobs, see <maml:navigationLink><maml:linkText>about_Jobs</maml:linkText><maml:uri></maml:uri></maml:navigationLink>.</maml:para></maml:description><command:parameterValue required="false" variableLength="false">SwitchParameter</command:parameterValue><dev:type><maml:name>SwitchParameter</maml:name><maml:uri /></dev:type><dev:defaultValue></dev:defaultValue></command:parameter><command:parameter required="false" variableLength="true" globbing="false" pipelineInput="false" position="named" aliases="Session"><maml:name>CimSession</maml:name><maml:description><maml:para>Runs the cmdlet in a remote session or on a remote computer. Enter a computer name or a session object, such as the output of a <maml:navigationLink><maml:linkText>New-CimSession</maml:linkText><maml:uri></maml:uri></maml:navigationLink> or <maml:navigationLink><maml:linkText>Get-CimSession</maml:linkText><maml:uri></maml:uri></maml:navigationLink> cmdlet. The default is the current session on the local computer.</maml:para></maml:description><command:parameterValue required="true" variableLength="true">CimSession[]</command:parameterValue><dev:type><maml:name>CimSession[]</maml:name><maml:uri /></dev:type><dev:defaultValue></dev:defaultValue></command:parameter><command:parameter required="false" variableLength="false" globbing="false" pipelineInput="false" position="named" aliases="Cn"><maml:name>ComputerName</maml:name><maml:description><maml:para>Specifies the DNS name, or IPv4 or IPv6 address, of the target computer running the DHCP server service.</maml:para></maml:description><command:parameterValue required="true" variableLength="false">String</command:parameterValue><dev:type><maml:name>String</maml:name><maml:uri /></dev:type><dev:defaultValue></dev:defaultValue></command:parameter><command:parameter required="false" variableLength="false" globbing="false" pipelineInput="True (ByPropertyName)" position="named" aliases=""><maml:name>Description</maml:name><maml:description><maml:para>Specifies the description to set on the scope.</maml:para></maml:description><command:parameterValue required="true" variableLength="false">String</command:parameterValue><dev:type><maml:name>String</maml:name><maml:uri /></dev:type><dev:defaultValue></dev:defaultValue></command:parameter><command:parameter required="false" variableLength="false" globbing="false" pipelineInput="True (ByPropertyName)" position="named" aliases=""><maml:name>Name</maml:name><maml:description><maml:para>Specifies the new name to set for the scope.</maml:para></maml:description><command:parameterValue required="true" variableLength="false">String</command:parameterValue><dev:type><maml:name>String</maml:name><maml:uri /></dev:type><dev:defaultValue></dev:defaultValue></command:parameter><command:parameter required="false" variableLength="false" globbing="false" pipelineInput="false" position="named" aliases=""><maml:name>PassThru</maml:name><maml:description><maml:para>Returns an object representing the item with which you are working. By default, this cmdlet does not generate any output.</maml:para></maml:description><command:parameterValue required="false" variableLength="false">SwitchParameter</command:parameterValue><dev:type><maml:name>SwitchParameter</maml:name><maml:uri /></dev:type><dev:defaultValue></dev:defaultValue></command:parameter><command:parameter required="false" variableLength="false" globbing="false" pipelineInput="True (ByPropertyName)" position="named" aliases=""><maml:name>Preference</maml:name><maml:description><maml:para>Specifies the preference value of the DHCP server service. The DHCP server service with the lowest preference value is selected by the DHCP client in case the client gets responses from more than one DHCP server service.</maml:para></maml:description><command:parameterValue required="true" variableLength="false">UInt16</command:parameterValue><dev:type><maml:name>UInt16</maml:name><maml:uri /></dev:type><dev:defaultValue></dev:defaultValue></command:parameter><command:parameter required="false" variableLength="false" globbing="false" pipelineInput="True (ByPropertyName)" position="named" aliases=""><maml:name>PreferredLifeTime</maml:name><maml:description><maml:para>Specifies the preferred life time of the IPv6 address leased by the DHCP server service. 
                         
This parameter value should be same or less than the ValidLifeTime parameter value.</maml:para></maml:description><command:parameterValue required="true" variableLength="false">TimeSpan</command:parameterValue><dev:type><maml:name>TimeSpan</maml:name><maml:uri /></dev:type><dev:defaultValue></dev:defaultValue></command:parameter><command:parameter required="true" variableLength="false" globbing="false" pipelineInput="True (ByPropertyName)" position="2" aliases=""><maml:name>Prefix</maml:name><maml:description><maml:para>Specifies the IPv6 subnet prefix of the scope for which the properties are modified.</maml:para></maml:description><command:parameterValue required="true" variableLength="false">IPAddress</command:parameterValue><dev:type><maml:name>IPAddress</maml:name><maml:uri /></dev:type><dev:defaultValue></dev:defaultValue></command:parameter><command:parameter required="false" variableLength="false" globbing="false" pipelineInput="True (ByPropertyName)" position="named" aliases=""><maml:name>State</maml:name><maml:description><maml:para>Specifies the state of the scope. The acceptable values for this parameter are:  Active or Inactive.</maml:para></maml:description><command:parameterValue required="true" variableLength="false">String</command:parameterValue><dev:type><maml:name>String</maml:name><maml:uri /></dev:type><dev:defaultValue></dev:defaultValue></command:parameter><command:parameter required="false" variableLength="false" globbing="false" pipelineInput="True (ByPropertyName)" position="named" aliases=""><maml:name>T1</maml:name><maml:description><maml:para>Specifies the lease renewal time. The DHCP client is expected to use a unicast message to renew the lease at the time specifies by this parameter value from the same DHCP server service from which DHCP client had initially obtained the lease. This parameter value should be less than the T2 and PreferredLifetime parameter values for the scope.</maml:para></maml:description><command:parameterValue required="true" variableLength="false">TimeSpan</command:parameterValue><dev:type><maml:name>TimeSpan</maml:name><maml:uri /></dev:type><dev:defaultValue></dev:defaultValue></command:parameter><command:parameter required="false" variableLength="false" globbing="false" pipelineInput="True (ByPropertyName)" position="named" aliases=""><maml:name>T2</maml:name><maml:description><maml:para>Specifies the lease rebind time. The client is expected to use a multi-cast message to renew the lease at the time equal to this parameter value from any DHCP server service if the renewal attempt at time specified by the T1 parameter fails. 
                         
This parameter value should be greater than the T1 parameter value and less than the PreferredLifetime parameter value.</maml:para></maml:description><command:parameterValue required="true" variableLength="false">TimeSpan</command:parameterValue><dev:type><maml:name>TimeSpan</maml:name><maml:uri /></dev:type><dev:defaultValue></dev:defaultValue></command:parameter><command:parameter required="false" variableLength="false" globbing="false" pipelineInput="false" position="named" aliases=""><maml:name>ThrottleLimit</maml:name><maml:description><maml:para>Specifies the maximum number of concurrent operations that can be established to run the cmdlet. If this parameter is omitted or a value of 0 is entered, then Windows PowerShell® calculates an optimum throttle limit for the cmdlet based on the number of CIM cmdlets that are running on the computer. The throttle limit applies only to the current cmdlet, not to the session or to the computer.</maml:para></maml:description><command:parameterValue required="true" variableLength="false">Int32</command:parameterValue><dev:type><maml:name>Int32</maml:name><maml:uri /></dev:type><dev:defaultValue></dev:defaultValue></command:parameter><command:parameter required="false" variableLength="false" globbing="false" pipelineInput="True (ByPropertyName)" position="named" aliases=""><maml:name>ValidLifeTime</maml:name><maml:description><maml:para>Specifies the valid life time of the IPv6 address leased by the DHCP server service. 
                         
This parameter value should be same or greater than the PreferredLifetime parameter value.</maml:para></maml:description><command:parameterValue required="true" variableLength="false">TimeSpan</command:parameterValue><dev:type><maml:name>TimeSpan</maml:name><maml:uri /></dev:type><dev:defaultValue></dev:defaultValue></command:parameter><command:parameter required="false" variableLength="true" globbing="false" pipelineInput="false" position="named"><maml:name>Confirm</maml:name><maml:description><maml:para>Prompts you for confirmation before running the cmdlet.</maml:para></maml:description><command:parameterValue required="false" variableLength="false">SwitchParameter</command:parameterValue><dev:type><maml:name>SwitchParameter</maml:name><maml:uri /></dev:type><dev:defaultValue>false</dev:defaultValue></command:parameter><command:parameter required="false" variableLength="true" globbing="false" pipelineInput="false" position="named"><maml:name>WhatIf</maml:name><maml:description><maml:para>Shows what would happen if the cmdlet runs. The cmdlet is not run.</maml:para></maml:description><command:parameterValue required="false" variableLength="false">SwitchParameter</command:parameterValue><dev:type><maml:name>SwitchParameter</maml:name><maml:uri /></dev:type><dev:defaultValue>false</dev:defaultValue></command:parameter></command:parameters><command:inputTypes><command:inputType><dev:type><maml:name>Microsoft.Management.Infrastructure.CimInstance#root/Microsoft/Windows/DHCP/DhcpServerv6Scope</maml:name><maml:uri>http://msdn.microsoft.com/library/hh832726.aspx</maml:uri><maml:description><maml:para /></maml:description></dev:type><maml:description><maml:para>The Microsoft.Management.Infrastructure.CimInstance object is a wrapper class that displays Windows Management Instrumentation (WMI) objects. The path after the pound sign (#) provides the namespace and class name for the underlying WMI object.</maml:para></maml:description></command:inputType></command:inputTypes><command:returnValues><command:returnValue><dev:type><maml:name>Microsoft.Management.Infrastructure.CimInstance#root/Microsoft/Windows/DHCP/DhcpServerv6Scope</maml:name><maml:uri>http://msdn.microsoft.com/library/hh832726.aspx</maml:uri><maml:description><maml:para /></maml:description></dev:type><maml:description><maml:para>The Microsoft.Management.Infrastructure.CimInstance object is a wrapper class that displays Windows Management Instrumentation (WMI) objects. The path after the pound sign (#) provides the namespace and class name for the underlying WMI object.</maml:para></maml:description></command:returnValue></command:returnValues><command:terminatingErrors /><command:nonTerminatingErrors /><command:examples><command:example><maml:title>EXAMPLE 1</maml:title><maml:introduction><maml:para></maml:para></maml:introduction><dev:code>PS C:\&gt;Set-DhcpServerv6Scope -ComputerName dhcpserver.contoso.com -Prefix 2001:4898:7020:1020:: -Name "Ext Lab Net VLAN100" -State Active

</dev:code><dev:remarks><maml:para>This example changes the name of the specified DHCPv6 scope to Ext Lab Net VLAN100 and activates the scope.</maml:para></dev:remarks><command:commandLines><command:commandLine><command:commandText /></command:commandLine></command:commandLines></command:example></command:examples><maml:relatedLinks><maml:navigationLink><maml:linkText>Online Version:</maml:linkText><maml:uri>http://go.microsoft.com/fwlink/?LinkID=289407</maml:uri></maml:navigationLink><maml:navigationLink><maml:linkText>Add-DhcpServerv6Scope</maml:linkText><maml:uri /></maml:navigationLink><maml:navigationLink><maml:linkText>Get-DhcpServerv6Scope</maml:linkText><maml:uri /></maml:navigationLink><maml:navigationLink><maml:linkText>Get-DhcpServerv6ScopeStatistics</maml:linkText><maml:uri /></maml:navigationLink><maml:navigationLink><maml:linkText>Remove-DhcpServerv6Scope</maml:linkText><maml:uri /></maml:navigationLink></maml:relatedLinks></command:command>

</helpItems>

